ytframedownloader/LICENSE
ytframedownloader/README.MD
ytframedownloader/__init__.py
ytframedownloader/requirements.txt
ytframedownloader/thirdparty.json
ytframedownloader-0.10.dist-info/LICENSE.rst
ytframedownloader-0.10.dist-info/METADATA
ytframedownloader-0.10.dist-info/WHEEL
ytframedownloader-0.10.dist-info/top_level.txt
ytframedownloader-0.10.dist-info/RECORD
