Metadata-Version: 2.1
Name: ytframedownloader
Version: 0.10
Summary: Download frames from videos
Home-page: https://github.com/hansalemaos/ytframedownloader
Author: Johannes Fischer
Author-email: <aulasparticularesdealemaosp@gmail.com>
License: MIT
Keywords: videos,frames
Classifier: Development Status :: 4 - Beta
Classifier: Programming Language :: Python :: 3 :: Only
Classifier: Programming Language :: Python :: 3.9
Classifier: Topic :: Scientific/Engineering :: Visualization
Classifier: Topic :: Software Development :: Libraries :: Python Modules
Classifier: Topic :: Text Editors :: Text Processing
Classifier: Topic :: Text Processing :: General
Classifier: Topic :: Text Processing :: Indexing
Classifier: Topic :: Text Processing :: Filters
Classifier: Topic :: Utilities
License-File: LICENSE.rst
Requires-Dist: a-pandas-ex-closest-neighbours
Requires-Dist: appdirs
Requires-Dist: pandas
Requires-Dist: regex
Requires-Dist: requests
